drepr/__init__.py
drepr/__main__.py
drepr/main.py
drepr/models/__init__.py
drepr/models/align.py
drepr/models/attr.py
drepr/models/drepr.py
drepr/models/drepr_builder.py
drepr/models/format.py
drepr/models/parsers/__init__.py
drepr/models/parsers/interface.py
drepr/models/parsers/v1/__init__.py
drepr/models/parsers/v1/align_parser.py
drepr/models/parsers/v1/attr_parser.py
drepr/models/parsers/v1/path_parser.py
drepr/models/parsers/v1/preprocessing_parser.py
drepr/models/parsers/v1/resource_parser.py
drepr/models/parsers/v1/sm_parser.py
drepr/models/parsers/v2/__init__.py
drepr/models/parsers/v2/path_parser.py
drepr/models/parsers/v2/sm_parser.py
drepr/models/parsers/v3/__init__.py
drepr/models/parsers/v3/sm_parser.py
drepr/models/path.py
drepr/models/prelude.py
drepr/models/preprocessing.py
drepr/models/resource.py
drepr/models/sm.py
drepr/planning/__init__.py
drepr/planning/class_map_plan.py
drepr/planning/drepr_model_alignments.py
drepr/planning/topological_sorting.py
drepr/program_generation/__init__.py
drepr/program_generation/alignment_fn.py
drepr/program_generation/main.py
drepr/program_generation/predefined_fn.py
drepr/program_generation/preprocessing.py
drepr/program_generation/program_space.py
drepr/program_generation/writers.py
drepr/readers/__init__.py
drepr/readers/csv.py
drepr/readers/json.py
drepr/readers/prelude.py
drepr/readers/spreadsheet.py
drepr/utils/__init__.py
drepr/utils/attr_data.py
drepr/utils/misc.py
drepr/utils/namespace_mixin.py
drepr/utils/safe.py
drepr/utils/udf.py
drepr/utils/validator.py
drepr/writers/__init__.py
drepr/writers/base.py
drepr/writers/rdflib_writer.py
drepr/writers/turtle_writer.py
drepr_v2-1.6.5.dist-info/WHEEL
drepr_v2-1.6.5.dist-info/METADATA
drepr_v2-1.6.5.dist-info/RECORD
