Metadata-Version: 2.3
Name: drepr-v2
Version: 1.6.5
Summary: 
Author: Binh Vu
Author-email: Binh Vu <binh@toan2.com>
Requires-Dist: orjson>=3.9.13
Requires-Dist: ruamel-yaml>=0.17.21
Requires-Dist: graph-wrapper>=1.7.1
Requires-Dist: serde2>=1.7.3
Requires-Dist: typer>=0.19.2
Requires-Dist: codegen-2>=2.15.2
Requires-Dist: rdflib>=7.0.0
Requires-Dist: openpyxl>=3.1.2
Requires-Dist: python-slugify>=8.0.4
Requires-Dist: autoflake>=2.2.1 ; extra == 'dev'
Requires-Dist: pytest>=8.0.0 ; extra == 'dev'
Requires-Dist: pytest-cov>=4.1.0 ; extra == 'dev'
Requires-Python: >=3.11
Provides-Extra: dev
